e_stat_dashboard_mcp/__init__.py
e_stat_dashboard_mcp/analytics.py
e_stat_dashboard_mcp/api_client.py
e_stat_dashboard_mcp/config.py
e_stat_dashboard_mcp/logging_config.py
e_stat_dashboard_mcp/normalizer.py
e_stat_dashboard_mcp/server.py
e_stat_dashboard_mcp/validation.py
e_stat_dashboard_mcp/visualizer.py
e_stat_dashboard_mcp-0.1.3.dist-info/METADATA
e_stat_dashboard_mcp-0.1.3.dist-info/WHEEL
e_stat_dashboard_mcp-0.1.3.dist-info/entry_points.txt
e_stat_dashboard_mcp-0.1.3.dist-info/RECORD
