Metadata-Version: 2.4
Name: e-stat-dashboard-mcp
Version: 0.1.3
Summary: Add your description here
Requires-Python: >=3.10
Requires-Dist: httpx>=0.28.1
Requires-Dist: japanize-matplotlib>=1.1.3
Requires-Dist: matplotlib>=3.10.8
Requires-Dist: mcp>=1.25.0
Requires-Dist: pandas-datareader>=0.10.0
Requires-Dist: pandas>=2.3.3
Requires-Dist: pydantic-settings>=2.12.0
Requires-Dist: pydantic>=2.12.5
Requires-Dist: python-dotenv>=1.2.1
Requires-Dist: seaborn>=0.13.2
